edgeofpy/__init__.py
edgeofpy/avalanche.py
edgeofpy/chaos.py
edgeofpy/synchrony.py
edgeofpy/utils.py
edgeofpy/VERSION
edgeofpy-0.0.1.dist-info/LICENSE
edgeofpy-0.0.1.dist-info/METADATA
edgeofpy-0.0.1.dist-info/WHEEL
edgeofpy-0.0.1.dist-info/RECORD
